{
  "scriptId": "147",
  "url": "https://deno.land/x/god_crypto@v0.2.0/src/helper.ts",
  "functions": [
    {
      "functionName": "",
      "ranges": [
        {
          "startOffset": 0,
          "endOffset": 17757,
          "count": 1
        }
      ],
      "isBlockCoverage": true
    },
    {
      "functionName": "str2bytes",
      "ranges": [
        {
          "startOffset": 7,
          "endOffset": 105,
          "count": 0
        }
      ],
      "isBlockCoverage": false
    },
    {
      "functionName": "hex",
      "ranges": [
        {
          "startOffset": 113,
          "endOffset": 254,
          "count": 0
        }
      ],
      "isBlockCoverage": false
    },
    {
      "functionName": "xor",
      "ranges": [
        {
          "startOffset": 262,
          "endOffset": 424,
          "count": 0
        }
      ],
      "isBlockCoverage": false
    },
    {
      "functionName": "concat",
      "ranges": [
        {
          "startOffset": 432,
          "endOffset": 693,
          "count": 0
        }
      ],
      "isBlockCoverage": false
    },
    {
      "functionName": "random_bytes",
      "ranges": [
        {
          "startOffset": 701,
          "endOffset": 871,
          "count": 0
        }
      ],
      "isBlockCoverage": false
    },
    {
      "functionName": "get_key_size",
      "ranges": [
        {
          "startOffset": 879,
          "endOffset": 1088,
          "count": 0
        }
      ],
      "isBlockCoverage": false
    },
    {
      "functionName": "base64_to_binary",
      "ranges": [
        {
          "startOffset": 1096,
          "endOffset": 3510,
          "count": 0
        }
      ],
      "isBlockCoverage": false
    }
  ]
}
